pynenc/__init__.py
pynenc/__main__.py
pynenc/app.py
pynenc/arg_cache/__init__.py
pynenc/arg_cache/base_arg_cache.py
pynenc/arg_cache/disabled_arg_cache.py
pynenc/arg_cache/mem_arg_cache.py
pynenc/arg_cache/redis_arg_cache.py
pynenc/arguments.py
pynenc/broker/__init__.py
pynenc/broker/base_broker.py
pynenc/broker/mem_broker.py
pynenc/broker/redis_broker.py
pynenc/builder.py
pynenc/call.py
pynenc/cli/__init__.py
pynenc/cli/config_cli.py
pynenc/cli/main_cli.py
pynenc/cli/monitor_cli.py
pynenc/cli/namespace.py
pynenc/cli/runner_cli.py
pynenc/conf/__init__.py
pynenc/conf/config_arg_cache.py
pynenc/conf/config_base.py
pynenc/conf/config_broker.py
pynenc/conf/config_orchestrator.py
pynenc/conf/config_pynenc.py
pynenc/conf/config_redis.py
pynenc/conf/config_runner.py
pynenc/conf/config_state_backend.py
pynenc/conf/config_task.py
pynenc/conf/config_trigger.py
pynenc/conf/constants.py
pynenc/context.py
pynenc/exceptions.py
pynenc/invocation/__init__.py
pynenc/invocation/base_invocation.py
pynenc/invocation/conc_invocation.py
pynenc/invocation/dist_invocation.py
pynenc/invocation/status.py
pynenc/orchestrator/__init__.py
pynenc/orchestrator/base_orchestrator.py
pynenc/orchestrator/mem_orchestrator.py
pynenc/orchestrator/redis_orchestrator.py
pynenc/pynenc/README.md
pynenc/runner/__init__.py
pynenc/runner/base_runner.py
pynenc/runner/multi_thread_runner.py
pynenc/runner/persistent_process_runner.py
pynenc/runner/process_runner.py
pynenc/runner/thread_runner.py
pynenc/serializer/__init__.py
pynenc/serializer/base_serializer.py
pynenc/serializer/constants.py
pynenc/serializer/json_serializer.py
pynenc/serializer/pickle_serializer.py
pynenc/state_backend/__init__.py
pynenc/state_backend/base_state_backend.py
pynenc/state_backend/mem_state_backend.py
pynenc/state_backend/redis_state_backend.py
pynenc/task.py
pynenc/trigger/__init__.py
pynenc/trigger/arguments/__init__.py
pynenc/trigger/arguments/argument_filters.py
pynenc/trigger/arguments/argument_providers.py
pynenc-0.0.24.dist-info/LICENSE
pynenc-0.0.24.dist-info/METADATA
pynenc-0.0.24.dist-info/WHEEL
pynenc-0.0.24.dist-info/entry_points.txt
pynenc-0.0.24.dist-info/RECORD
