Metadata-Version: 2.1
Name: pynenc
Version: 0.0.24
Summary: A task management system for complex distributed orchestration
Home-page: https://pynenc.org
License: MIT
Author: Jose Diaz
Requires-Python: >=3.11.6
Classifier: Development Status :: 3 - Alpha
Classifier: Intended Audience :: Developers
Classifier: License :: OSI Approved :: MIT License
Classifier: Programming Language :: Python :: 3
Classifier: Programming Language :: Python :: 3.12
Classifier: Programming Language :: Python :: 3.11
Classifier: Topic :: Software Development :: Libraries :: Python Modules
Classifier: Topic :: System :: Distributed Computing
Provides-Extra: monitor
Requires-Dist: cistell (==0.0.7)
Requires-Dist: croniter (>=6.0.0,<7.0.0)
Requires-Dist: fastapi (>=0.115.11,<0.116.0) ; extra == "monitor"
Requires-Dist: jinja2 (>=3.1.4,<4.0.0) ; extra == "monitor"
Requires-Dist: python-multipart (>=0.0.6,<0.1.0) ; extra == "monitor"
Requires-Dist: pyyaml (>=6.0.1)
Requires-Dist: redis (>=4.6.0)
Requires-Dist: typing-extensions (>=4.9.0,<5.0.0)
Requires-Dist: uvicorn (>=0.34.0,<0.35.0) ; extra == "monitor"
Project-URL: Documentation, https://docs.pynenc.org
Project-URL: Repository, https://github.com/pynenc/pynenc
